funcio/__init__.py
funcio/bytes.py
funcio/exception.py
funcio/input.py
funcio/message.py
funcio/output.py
funcio/test_bytes.py
funcio/test_input.py
funcio/test_output.py
predix_funcio-1.0.2.dist-info/DESCRIPTION.rst
predix_funcio-1.0.2.dist-info/METADATA
predix_funcio-1.0.2.dist-info/RECORD
predix_funcio-1.0.2.dist-info/WHEEL
predix_funcio-1.0.2.dist-info/metadata.json
predix_funcio-1.0.2.dist-info/top_level.txt
