Metadata-Version: 2.0
Name: predix-funcio
Version: 1.0.2
Summary: Helper library for predix python lambda functions running in hot containers
Home-page: http://predix.io
Author: Timothy Farkas
Author-email: timothy.farkas@ge.com
License: Apache Software License
Keywords: predix lambda
Platform: UNKNOWN
Classifier: Development Status :: 3 - Alpha
Classifier: Intended Audience :: Developers
Classifier: Topic :: Software Development :: Build Tools
Classifier: License :: OSI Approved :: Apache Software License
Classifier: Programming Language :: Python :: 2.7
